<?xml version="1.0" encoding="UTF-8"?>
<interface>
  <object class="GtkMenu" id="menu">
    <child>
	<object class="GtkMenuItem" id="disconnect">
		<property name="label">Disconnect wifi</property>
        </object>
    </child>
    <child>
      <object class="GtkSeparatorMenuItem" id="delimiter1"/>
    </child>
    <child>
	<object class="GtkMenuItem" id="reconnect">
		<property name="label">Reconnect wifi</property>
        </object>
    </child>
    <child>
      <object class="GtkSeparatorMenuItem" id="delimiter"/>
    </child>
    <child>
	<object class="GtkMenuItem" id="gui">
		<property name="label">Open GUI</property>
        </object>
    </child>
  </object>
</interface>
